ckanext/__init__.py
ckanext/statistics/__init__.py
ckanext/statistics/plugin.py
ckanext/statistics/data/data-portal-backfill.json
ckanext/statistics/lib/__init__.py
ckanext/statistics/lib/dataset_statistics.py
ckanext/statistics/lib/download_statistics.py
ckanext/statistics/lib/gbif_api.py
ckanext/statistics/lib/statistics.py
ckanext/statistics/logic/__init__.py
ckanext/statistics/logic/action.py
ckanext/statistics/logic/schema.py
ckanext/statistics/migration/statistics/README
ckanext/statistics/migration/statistics/alembic.ini
ckanext/statistics/migration/statistics/env.py
ckanext/statistics/migration/statistics/script.py.mako
ckanext/statistics/migration/statistics/versions/1d68ab53e0bb_initialisation.py
ckanext/statistics/model/__init__.py
ckanext/statistics/model/ckanpackager.py
ckanext_statistics-4.0.1.dist-info/licenses/LICENSE
docs/_scripts/gen_api_pages.py
ckanext_statistics-4.0.1.dist-info/METADATA
ckanext_statistics-4.0.1.dist-info/WHEEL
ckanext_statistics-4.0.1.dist-info/entry_points.txt
ckanext_statistics-4.0.1.dist-info/top_level.txt
ckanext_statistics-4.0.1.dist-info/RECORD
