Metadata-Version: 2.4
Name: ckanext-statistics
Version: 4.0.1
Summary: A CKAN extension for accessing instance statistics.
Author-email: Natural History Museum <data@nhm.ac.uk>
License: GPL-3.0-or-later
Project-URL: repository, https://github.com/NaturalHistoryMuseum/ckanext-statistics
Project-URL: changelog, https://github.com/NaturalHistoryMuseum/ckanext-statistics/blob/main/CHANGELOG.md
Keywords: CKAN,data,statistics
Classifier: Development Status :: 5 - Production/Stable
Classifier: License :: OSI Approved :: GNU General Public License v3 (GPLv3)
Classifier: Programming Language :: Python
Classifier: Programming Language :: Python :: 3 :: Only
Classifier: Programming Language :: Python :: 3.6
Classifier: Programming Language :: Python :: 3.7
Classifier: Programming Language :: Python :: 3.8
Requires-Python: >=3.6
License-File: LICENSE
Requires-Dist: importlib-resources
Requires-Dist: requests
Requires-Dist: tqdm>=4.55.1
Requires-Dist: ckanext-versioned-datastore>=5.1.0
Requires-Dist: ckantools>=0.4.2
Provides-Extra: test
Requires-Dist: mock; extra == "test"
Requires-Dist: pytest>=4.6.5; extra == "test"
Requires-Dist: pytest-cov>=2.7.1; extra == "test"
Requires-Dist: coveralls; extra == "test"
Dynamic: license-file
